{
  "items": [
    {
      "videoId": "h6RFCXOvsKg",
      "title": "[Plus LIVE Epilogue] XODIAC Plus LIVE Epilogue",
      "thumbnails": {
        "url": "https://i.ytimg.com/vi/h6RFCXOvsKg/hqdefault.jpg"
      }
    },
    {
      "videoId": "8adNqoCTAH8",
      "title": "[Plus LIVE Epilogue] 엠비셔스 Plus LIVE 에필로그",
      "thumbnails": {
        "url": "https://i.ytimg.com/vi/8adNqoCTAH8/hqdefault.jpg"
      }
    },
    {
      "videoId": "xuFAOXPffTw",
      "title": "[Plus LIVE Epilogue] iKON Plus LIVE Epilogue",
      "thumbnails": {
        "url": "https://i.ytimg.com/vi/xuFAOXPffTw/hqdefault.jpg"
      }
    },
    {
      "videoId": "hHK6pos5RJM",
      "title": "[Plus LIVE Epilogue] 1MILLION Plus LIVE Epilogue",
      "thumbnails": {
        "url": "https://i.ytimg.com/vi/hHK6pos5RJM/hqdefault.jpg"
      }
    },
    {
      "videoId": "gNL3_1VxM-0",
      "title": "[Plus LIVE Epilogue] 케이 Plus LIVE 에필로그",
      "thumbnails": {
        "url": "https://i.ytimg.com/vi/gNL3_1VxM-0/hqdefault.jpg"
      }
    },
    {
      "videoId": "GykhQTqs9R0",
      "title": "[Plus LIVE Epilogue] MANNEQUEEN Plus LIVE Epilogue",
      "thumbnails": {
        "url": "https://i.ytimg.com/vi/GykhQTqs9R0/hqdefault.jpg"
      }
    },
    {
      "videoId": "DVjpMebfG64",
      "title": "[Plus LIVE Epilogue] BEBE Plus LIVE Epilogue",
      "thumbnails": {
        "url": "https://i.ytimg.com/vi/DVjpMebfG64/hqdefault.jpg"
      }
    },
    {
      "videoId": "8gl2U8vJoMk",
      "title": "[Plus LIVE  Epilogue] EVNNE Plus LIVE  Epilogue",
      "thumbnails": {
        "url": "https://i.ytimg.com/vi/8gl2U8vJoMk/hqdefault.jpg"
      }
    }
  ]
}